bmxp/__init__.py
bmxp/blueshift/__init__.py
bmxp/blueshift/blueshift_example.py
bmxp/chroma/__init__.py
bmxp/chroma/accessions.py
bmxp/chroma/base64.h
bmxp/chroma/full_test.py
bmxp/chroma/main.c
bmxp/chroma/main.py
bmxp/chroma/main_dataclasses.py
bmxp/chroma/mzml_parser.py
bmxp/chroma/numpress.c
bmxp/chroma/parsefinnigan.c
bmxp/chroma/parsemzml.c
bmxp/chroma/rawfile.c
bmxp/chroma/rawfilereader.dll
bmxp/chroma/rawfilereader.so
bmxp/chroma/readme.md
bmxp/chroma/temp_use_avg.py
bmxp/chroma/temp_use_rtfirstlast.py
bmxp/eclipse/__init__.py
bmxp/eclipse/eclipse_example.py
bmxp/formation/__init__.py
bmxp/formation/formation_plots.py
bmxp/gravity/__init__.py
bmxp/gravity/correlation.c
bmxp/gravity/correlation.dll
bmxp/gravity/correlation.so
bmxp/gravity/fallback.py
bmxp/gravity/gravity_example.py
bmxp-0.4.8.dist-info/licenses/LICENSE
bmxp-0.4.8.dist-info/METADATA
bmxp-0.4.8.dist-info/WHEEL
bmxp-0.4.8.dist-info/top_level.txt
bmxp-0.4.8.dist-info/RECORD
