Metadata-Version: 2.4
Name: bmxp
Version: 0.4.8
Summary: LCMS Processing tools used by the Metabolomics Platform at the Broad Institute.
Author: Daniel S. Hitchcock, Jesse Krejci, Jayanth Mani, Chloe Sturgeon
Author-email: "Daniel S. Hitchcock" <daniel.s.hitchcock@gmail.com>
License: MIT
Project-URL: Repository, https://github.com/broadinstitute/bmxp
Keywords: LCMS,Alignment,Processing,Metabolomics,Clustering,Batch Correction,Drift Correction,QC,Filtering
Classifier: License :: OSI Approved :: MIT License
Classifier: Programming Language :: Python :: 3
License-File: LICENSE
Requires-Dist: networkx
Requires-Dist: pandas>=2
Requires-Dist: scipy>=1
Requires-Dist: statsmodels
Requires-Dist: matplotlib
Requires-Dist: scikit-learn>=1
Requires-Dist: xlsxwriter
Requires-Dist: openpyxl
Requires-Dist: tqdm
Dynamic: license-file
